{
    "wheeled01": {
        "buildPoints": 0,
        "buildPower": 0,
        "designable": 1,
        "hitpointPctOfBody": 100,
        "id": "wheeled01",
        "model": "PRLWHL1.PIE",
        "name": "Wheels",
        "skidDeceleration": 350,
        "speed": 1024,
        "type": "Wheeled",
        "weight": 120
    },
    "hover01": {
        "buildPoints": 0,
        "buildPower": 0,
        "designable": 1,
        "hitpointPctOfBody": 0,
        "id": "hover01",
        "model": "PRLHOV1.PIE",
        "name": "Hover",
        "skidDeceleration": 200,
        "speed": 1024,
        "type": "Hover",
        "weight": 20
    },
    "tracked01": {
        "buildPoints": 0,
        "buildPower": 0,
        "designable": 1,
        "hitpointPctOfBody": 300,
        "id": "tracked01",
        "model": "PRLTRK1.PIE",
        "name": "Tracks",
        "speed": 1024,
        "spinAngle": 45,
        "type": "Tracked",
        "weight": 200
    },
    "V-Tol": {
        "acceleration": 400,
        "buildPoints": 25,
        "buildPower": 25,
        "deceleration": 128,
        "designable": 1,
        "hitpointPctOfBody": 50,
        "id": "V-Tol",
        "model": "DPVTOL.PIE",
        "name": "VTOL",
        "speed": 1024,
        "spinSpeed": 50,
        "turnSpeed": 150,
        "type": "Lift",
        "weight": 50
    },
    "BaBaLegs": {
        "buildPoints": 15,
        "deceleration": 450,
        "id": "BaBaLegs",
        "name": "BaBaLegs",
        "speed": 200,
        "spinAngle": 45,
        "spinSpeed": 450,
        "turnSpeed": 225,
        "type": "Legged",
        "weight": 10
    },
    "BaBaProp": {
        "buildPoints": 15,
        "id": "BaBaProp",
        "name": "BaBaProp",
        "speed": 200,
        "type": "Wheeled",
        "weight": 10
    },
    "ZNULLPROP": {
        "id": "ZNULLPROP",
        "model": "znulltracks.pie",
        "name": "Z NULL PROP",
        "type": "Wheeled"
    }
}
